app_store_scraper/__init__.py
app_store_scraper/__version__.py
app_store_scraper/app_store.py
app_store_scraper/base.py
app_store_scraper/podcast.py
python_app_store_scraper-1.1.1.dist-info/LICENSE
python_app_store_scraper-1.1.1.dist-info/METADATA
python_app_store_scraper-1.1.1.dist-info/WHEEL
python_app_store_scraper-1.1.1.dist-info/top_level.txt
python_app_store_scraper-1.1.1.dist-info/RECORD
