Metadata-Version: 2.1
Name: python-app-store-scraper
Version: 1.1.1
Summary: An Awesome App Store Review Scraper 🧹
Home-page: https://github.com/iamfoysal/py-app-store
Author: Mohammad Foysal
License: MIT
Project-URL: Source, https://github.com/iamfoysal/py-app-store
Keywords: app store,ios,ios apps,podcasts,review,scraping,scraper
Classifier: Intended Audience :: Developers
Classifier: License :: OSI Approved :: MIT License
Classifier: Natural Language :: English
Classifier: Operating System :: OS Independent
Classifier: Programming Language :: Python :: 3
Classifier: Programming Language :: Python :: 3.6
Classifier: Programming Language :: Python :: 3.7
Classifier: Programming Language :: Python :: 3.8
Classifier: Topic :: Internet :: WWW/HTTP
Classifier: Topic :: Scientific/Engineering :: Information Analysis
Requires-Python: >=3.6
License-File: LICENSE
Requires-Dist: requests (==2.31.0)
